flake8_requirements/__init__.py
flake8_requirements/checker.py
flake8_requirements/modules.py
flake8_requirements_absolute_imports-1.6.0.1.dist-info/LICENSE.txt
flake8_requirements_absolute_imports-1.6.0.1.dist-info/METADATA
flake8_requirements_absolute_imports-1.6.0.1.dist-info/WHEEL
flake8_requirements_absolute_imports-1.6.0.1.dist-info/entry_points.txt
flake8_requirements_absolute_imports-1.6.0.1.dist-info/top_level.txt
flake8_requirements_absolute_imports-1.6.0.1.dist-info/RECORD
