Metadata-Version: 2.1
Name: flake8-requirements-absolute-imports
Version: 1.6.0.1
Summary: Package requirements checker, plugin for flake8
Home-page: https://github.com/Arkq/flake8-requirements
Author: Arkadiusz Bokowy
Author-email: arkadiusz.bokowy@gmail.com
License: MIT
Platform: UNKNOWN
Classifier: Framework :: Flake8
Classifier: Intended Audience :: Developers
Classifier: License :: OSI Approved :: MIT License
Classifier: Programming Language :: Python
Classifier: Programming Language :: Python :: 2
Classifier: Programming Language :: Python :: 3
Classifier: Topic :: Software Development :: Libraries :: Python Modules
Classifier: Topic :: Software Development :: Quality Assurance
Requires-Dist: flake8 (>=2.0.0)
Requires-Dist: setuptools (>=10.0.0)
Requires-Dist: toml (>=0.7.0)
